novas3d/.ipynb_checkpoints/vessel_graph-checkpoint.py
novas3d/__init__.py
novas3d/predict.py
novas3d/registration.py
novas3d/utilities.py
novas3d/vessel_graph.py
novas3d-0.1.10.dist-info/METADATA
novas3d-0.1.10.dist-info/WHEEL
novas3d-0.1.10.dist-info/RECORD
