Metadata-Version: 2.1
Name: novas3d
Version: 0.1.10
Summary: 
Author: Matthew Rozak
Author-email: matthew.rozak@mail.utoronto.ca
Requires-Python: >=3.8,<3.13
Classifier: Programming Language :: Python :: 3
Classifier: Programming Language :: Python :: 3.8
Classifier: Programming Language :: Python :: 3.9
Classifier: Programming Language :: Python :: 3.10
Classifier: Programming Language :: Python :: 3.11
Classifier: Programming Language :: Python :: 3.12
Requires-Dist: antspyx
Requires-Dist: anyio (==4.5.0)
Requires-Dist: connected-components-3d
Requires-Dist: einops (==0.3.2)
Requires-Dist: ignite (==1.1.0)
Requires-Dist: imageio (==2.28.0)
Requires-Dist: ipython (==7.34.0)
Requires-Dist: jsonschema-specifications (==2023.3.6)
Requires-Dist: jupyter
Requires-Dist: matplotlib (==3.4.2)
Requires-Dist: monai (>=0.8.0,<=0.9.0)
Requires-Dist: networkx (==2.6.3)
Requires-Dist: nibabel (==3.2.1)
Requires-Dist: notebook
Requires-Dist: numpy (<2.0.0)
Requires-Dist: pyparsing (==3.1.0)
Requires-Dist: pytorch-ignite
Requires-Dist: pytransform3d (==2.1.0)
Requires-Dist: scikit-image (<0.22.0)
Requires-Dist: scikit-learn
Requires-Dist: scipy
Requires-Dist: sknw
Requires-Dist: tifffile (==2021.11.2)
Requires-Dist: torch (<2.0.0)
Requires-Dist: tqdm (>=4.66.5,<5.0.0)
Requires-Dist: typing-extensions (>=4.1)
Requires-Dist: vg (==2.0.0)
